[
  {
    "id": 1,
    "name": "Alcenio Elpidio",
    "calendarId": "0ca7e99a558f60e928a3e775ab8d5bf0949630d14a37f2ae542646411f569044@group.calendar.google.com",
    "location": "Paranaíba, MS, Brasil",
    "normalizedCountryCode": "BR",
    "languages": ["pt", "es"],
    "formUrl": "https://forms.gle/FCcjntfuuoGoGLtx5"
  },
  {
    "id": 2,
    "name": "Daniel Munoz",
    "calendarId": "47d6c4ce5a6c1efcce8f7a40abaf38ad59995d62194d27170aba63b1bd184dd8@group.calendar.google.com",
    "location": "Bothell, WA, USA",
    "normalizedCountryCode": "US",
    "languages": ["en", "es", "pt"],
    "formUrl": "https://forms.gle/8y8kycv8ZFndSmAc6"
  },
  {
    "id": 3,
    "name": "Josianne Tavares",
    "calendarId": "f5ce6655ed5feb654a23a79d2dda755debd873372ec8353551b972c5cb747c61@group.calendar.google.com",
    "location": "Brasília, DF, Brasil",
    "normalizedCountryCode": "BR",
    "languages": ["pt"],
    "formUrl": "https://forms.gle/bVL1ByhmG4wbAMKb7",
    "children6to8": true,
    "children9to12": true
  },
  {
    "id": 4,
    "name": "Omar Fino",
    "calendarId": "c79d0abe72d68b4ea0eb7e671c45e84eaccd41b959eab558761c04dda2ffe9ac@group.calendar.google.com",
    "location": "Moquegua, Perú",
    "normalizedCountryCode": "PE",
    "languages": ["es", "pt"],
    "formUrl": "https://forms.gle/gAJFxmU3XBBwVFrP6",
    "children6to8": true,
    "children9to12": true
  },
  {
    "id": 5,
    "name": "Sara Oquendo",
    "calendarId": "deb8969c4b0637ca9008efe6ca694631142f43b88c70c533eb2c34808c1e75ec@group.calendar.google.com",
    "location": "Moquegua, Perú",
    "normalizedCountryCode": "PE",
    "languages": ["es", "pt"],
    "formUrl": "https://forms.gle/DVGmCpqH4QDmjFP58",
    "children6to8": true,
    "children9to12": true
  },
  {
    "id": 6,
    "name": "Raquel Oquendo",
    "calendarId": "4667389ecf273bdcbe538106ec17c410f08bfc68f853e91e14e31ad303059aea@group.calendar.google.com",
    "location": "Moquegua, Perú",
    "normalizedCountryCode": "PE",
    "languages": ["es"],
    "formUrl": "https://forms.gle/kRExifPWRfFdgkts5"
  },
  {
    "id": 7,
    "name": "Elia Melendez",
    "calendarId": "6a1c50d5b87b24787c01131ee7f6abd2aa8b8284f2966dbf1e0531f6514e8d8d@group.calendar.google.com",
    "location": "Moquegua, Perú",
    "normalizedCountryCode": "PE",
    "languages": ["es"],
    "formUrl": "https://forms.gle/TYnna4sFNLTETtMc6"
  },
  {
    "id": 8,
    "name": "Sirlene Silva",
    "calendarId": "54e0b886bae92e14236e2823f424df52bc0ee1fb2b0b3afcdeb612b6fcca1d16@group.calendar.google.com",
    "location": "Quatro Barras, PR, Brasil",
    "normalizedCountryCode": "BR",
    "languages": ["pt"],
    "formUrl": "https://docs.google.com/forms/d/e/1FAIpQLSfg7FwEokvUPHs5n_FVcaOG7drzc7NJw4MLZmaUqThobYpQfg/viewform"
  },
  {
    "id": 9,
    "name": "Thiago Soares",
    "calendarId": "0603a19b52adaa2dcfbd4a9de8384a2650c615a4d0bad740f781ada2233c9aa2@group.calendar.google.com",
    "location": "Campo Grande, MS, Brasil",
    "normalizedCountryCode": "BR",
    "languages": ["es", "pt"],
    "formUrl": "https://docs.google.com/forms/d/e/1FAIpQLSeuAa92Pfq3YSr3bAetd9-h5yM4mX5pavDDutjNV9xBmv4ySg/viewform"
  },
  {
    "id": 10,
    "name": "Ivori Junior",
    "calendarId": "6b4b3fc3eb9b094732ca21cf7f6dd4c32103350233579b57add7df5893b7d7da@group.calendar.google.com",
    "location": "Saõ Paulo / Hortolândia (ambos), SP, Brasil",
    "normalizedCountryCode": "BR",
    "languages": ["pt"],
    "formUrl": "https://docs.google.com/forms/d/e/1FAIpQLSdPWWWZ2OvADEihWamlO7lPVekhzQku0R7U0hGb4JHibfzXXw/viewform"
  },
  {
    "id": 11,
    "name": "Márcia Sousa",
    "calendarId": "cddf180922a4bc1c07833bb34e68143205deef34bc7c60c14db6eec8331ecf4f@group.calendar.google.com",
    "location": "Taubaté, SP, Brasil",
    "normalizedCountryCode": "BR",
    "languages": ["pt"],
    "formUrl": "https://forms.gle/aLuFSeyrD56ML1Fi7",
    "children6to8": true,
    "children9to12": true
  },
  {
    "id": 12,
    "name": "Cleuza Biazotto",
    "calendarId": "b245438cab25e6b82cace21e0176e4585625fa1ebeb9b08b8eb22f3afb82e508@group.calendar.google.com",
    "location": "Mirandópolis, SP, Brasil",
    "normalizedCountryCode": "BR",
    "languages": ["pt"],
    "formUrl": "https://forms.gle/Uu4oAnyCDphGhCgN7"
  },
  {
    "id": 13,
    "name": "Ildamar Farias",
    "calendarId": "a45f6aa091490cd8085550fdd8fa67c21fae9924659d29553a0ee1fa0d75e36b@group.calendar.google.com",
    "location": "Brasília, DF, Brasil",
    "normalizedCountryCode": "BR",
    "languages": ["pt"],
    "formUrl": "https://forms.gle/49XW21uJTC7cuVaC6"
  },
  {
    "id": 14,
    "name": "Gilson Nunes",
    "calendarId": "042b1ab9a7346c003cc55b73e717d8e1169ff9201ae9442ac9f6bf390ac9830d@group.calendar.google.com",
    "location": "Belém, PA, Brasil",
    "normalizedCountryCode": "BR",
    "languages": ["pt"],
    "formUrl": "https://forms.gle/RHYPkzmtArBfoqqF6"
  }
]
